infinity_grid/__init__.py
infinity_grid/_version.py
infinity_grid/exceptions.py
infinity_grid/adapters/__init__.py
infinity_grid/adapters/exchange_registry.py
infinity_grid/adapters/notification.py
infinity_grid/adapters/exchanges/__init__.py
infinity_grid/adapters/exchanges/kraken.py
infinity_grid/core/__init__.py
infinity_grid/core/cli.py
infinity_grid/core/engine.py
infinity_grid/core/event_bus.py
infinity_grid/core/state_machine.py
infinity_grid/infrastructure/__init__.py
infinity_grid/infrastructure/database.py
infinity_grid/interfaces/__init__.py
infinity_grid/interfaces/exchange.py
infinity_grid/interfaces/notification.py
infinity_grid/models/__init__.py
infinity_grid/models/configuration.py
infinity_grid/models/exchange.py
infinity_grid/services/__init__.py
infinity_grid/services/database.py
infinity_grid/services/metrics_service.py
infinity_grid/services/notification_service.py
infinity_grid/strategies/__init__.py
infinity_grid/strategies/c_dca.py
infinity_grid/strategies/grid_base.py
infinity_grid/strategies/grid_hodl.py
infinity_grid/strategies/grid_sell.py
infinity_grid/strategies/swing.py
infinity_grid-1.3.4.dist-info/licenses/LICENSE
infinity_grid-1.3.4.dist-info/METADATA
infinity_grid-1.3.4.dist-info/WHEEL
infinity_grid-1.3.4.dist-info/entry_points.txt
infinity_grid-1.3.4.dist-info/top_level.txt
infinity_grid-1.3.4.dist-info/RECORD
