Metadata-Version: 2.4
Name: infinity-grid
Version: 1.3.4
Summary: Multi-exchange Infinity Grid Trading Algorithm
Author-email: Benjamin Thomas Schwertfeger <contact@b-schwertfeger.de>
License-Expression: LicenseRef-Infinity-Grid-2.0
Project-URL: Homepage, https://github.com/btschwertfeger/infinity-grid
Project-URL: Documentation, https://infinity-grid.readthedocs.io/en/stable/
Project-URL: Changelog, https://github.com/btschwertfeger/infinity-grid/releases
Project-URL: Bug Tracker, https://github.com/btschwertfeger/infinity-grid/issues
Keywords: crypto,trading,trading bot,grid trading,exchange
Classifier: Development Status :: 5 - Production/Stable
Classifier: Environment :: Console
Classifier: Framework :: AsyncIO
Classifier: Framework :: Pytest
Classifier: Natural Language :: English
Classifier: Operating System :: MacOS
Classifier: Operating System :: Unix
Classifier: Programming Language :: Python :: 3.11
Classifier: Programming Language :: Python :: 3.12
Classifier: Programming Language :: Python :: 3.13
Classifier: Programming Language :: Python
Classifier: Topic :: Internet :: WWW/HTTP
Classifier: Topic :: Office/Business :: Financial :: Investment
Classifier: Topic :: Office/Business :: Financial
Classifier: Typing :: Typed
Requires-Python: >=3.11
License-File: LICENSE
Requires-Dist: aiohttp~=3.12
Requires-Dist: click~=8.1
Requires-Dist: cloup~=3.0
Requires-Dist: requests~=2.32
Requires-Dist: psycopg2-binary~=2.9
Requires-Dist: sqlalchemy~=2.0
Requires-Dist: pydantic~=2.11
Provides-Extra: kraken
Requires-Dist: python-kraken-sdk<4.0.0,>=3.2.6; extra == "kraken"
Dynamic: license-file
